freeotp_extractor/Extractor.py
freeotp_extractor/__init__.py
freeotp_extractor-0.3.1.dist-info/LICENSE
freeotp_extractor-0.3.1.dist-info/METADATA
freeotp_extractor-0.3.1.dist-info/WHEEL
freeotp_extractor-0.3.1.dist-info/entry_points.txt
freeotp_extractor-0.3.1.dist-info/top_level.txt
freeotp_extractor-0.3.1.dist-info/RECORD
