Metadata-Version: 2.1
Name: freeotp-extractor
Version: 0.3.1
Summary: Extract tokens from FreeOTP backup
Home-page: https://gitlab.com/Oprax/freeotp-extractor
Author: Oprax
Author-email: oprax@me.com
License: MIT
Platform: UNKNOWN
Classifier: Programming Language :: Python :: 3
Classifier: Programming Language :: Python :: 3.6
Classifier: Programming Language :: Python :: 3.7
Classifier: License :: OSI Approved :: MIT License
Classifier: Development Status :: 4 - Beta
Classifier: Environment :: Console
Classifier: Operating System :: POSIX
Requires-Dist: pyqrcode
Requires-Dist: awesome-slugify
